MANIFEST.in
README.md
pmap.py
requirements.txt
setup.py
pmap.egg-info/PKG-INFO
pmap.egg-info/SOURCES.txt
pmap.egg-info/dependency_links.txt
pmap.egg-info/requires.txt
pmap.egg-info/top_level.txt