Metadata-Version: 1.0
Name: pmap
Version: 0.0.6
Summary: a multithreaded map operator
Home-page: UNKNOWN
Author: Francesco Bruschi
Author-email: bruschi@elet.polimi.it
License: UNKNOWN
Platform: UNKNOWN
